gradescope_mean/__init__.py
gradescope_mean/__main__.py
gradescope_mean/assign_list.py
gradescope_mean/banner/__init__.py
gradescope_mean/banner/__main__.py
gradescope_mean/canvas/__init__.py
gradescope_mean/canvas/__main__.py
gradescope_mean/canvas/canvas.py
gradescope_mean/config.py
gradescope_mean/config.yaml
gradescope_mean/get_mean_drop_low.py
gradescope_mean/gradebook.py
gradescope_mean/perc_to_letter.py
gradescope_mean/plot.py
gradescope_mean-0.0.17.dist-info/METADATA
gradescope_mean-0.0.17.dist-info/WHEEL
gradescope_mean-0.0.17.dist-info/licenses/LICENSE
gradescope_mean-0.0.17.dist-info/RECORD
