Metadata-Version: 2.4
Name: gradescope-mean
Version: 0.0.17
Summary: Utility to average gradescope csv output to final grades
License-File: LICENSE
Author: Matt Higger
Author-email: mhigger@ccs.neu.edu
Requires-Python: >=3.10
Classifier: Programming Language :: Python :: 3
Classifier: Programming Language :: Python :: 3.10
Classifier: Programming Language :: Python :: 3.11
Classifier: Programming Language :: Python :: 3.12
Classifier: Programming Language :: Python :: 3.13
Classifier: Programming Language :: Python :: 3.14
Requires-Dist: numpy (>=2.2.2,<3.0.0)
Requires-Dist: openpyxl (>=3.1.5,<4.0.0)
Requires-Dist: pandas (>=2.2.3,<3.0.0)
Requires-Dist: plotly (>=6.0.0,<7.0.0)
Requires-Dist: ruamel-yaml (>=0.18.10,<0.19.0)
